pytagit/CNNTrainer.py
pytagit/ConfigDialog.py
pytagit/Helpers.py
pytagit/ImageGallery.py
pytagit/OOD4Inclusion.py
pytagit/QFlowLayout.py
pytagit/TSNEDialog.py
pytagit/__init__.py
pytagit/main.py
pytagit-0.1.6.dist-info/licenses/LICENCE.md
pytagit-0.1.6.dist-info/METADATA
pytagit-0.1.6.dist-info/WHEEL
pytagit-0.1.6.dist-info/entry_points.txt
pytagit-0.1.6.dist-info/top_level.txt
pytagit-0.1.6.dist-info/RECORD
