Metadata-Version: 2.4
Name: pytagit
Version: 0.1.6
Summary: Interactive tool for image tagging with the human in the loop
Home-page: https://github.com/dros1986/pytagit
Author: Flavio Piccoli
Author-email: dros1986@gmail.com
License: CC-BY-NC-4.0
Keywords: image tagging,interactive tool,human in the loop,pytorch,PyQt6,t-SNE,CNN training
Classifier: Programming Language :: Python :: 3
Classifier: Operating System :: OS Independent
Classifier: Environment :: X11 Applications :: Qt
Classifier: Intended Audience :: Science/Research
Classifier: Topic :: Scientific/Engineering :: Image Recognition
Requires-Python: >=3.8
License-File: LICENCE.md
Requires-Dist: torch>=2.0.0
Requires-Dist: torchvision>=0.15.0
Requires-Dist: numpy>=1.23
Requires-Dist: PyQt6>=6.5
Requires-Dist: scikit-learn>=1.3
Requires-Dist: matplotlib>=3.7
Requires-Dist: albumentations>=1.3
Requires-Dist: einops>=0.6
Requires-Dist: opencv-python>=4.8
Requires-Dist: Pillow>=9.5
Requires-Dist: tqdm>=4.65
Requires-Dist: regex>=2023
Requires-Dist: pandas>=2.0
Requires-Dist: transformers>=4.50
Requires-Dist: pytorch-lightning>=2.5
Requires-Dist: openTSNE>=1.0
Requires-Dist: seaborn>=0.13
Requires-Dist: rich>=12.0.0
Dynamic: author
Dynamic: author-email
Dynamic: classifier
Dynamic: description
Dynamic: description-content-type
Dynamic: home-page
Dynamic: keywords
Dynamic: license
Dynamic: license-file
Dynamic: requires-dist
Dynamic: requires-python
Dynamic: summary
